nametrans/__init__.py
nametrans/callbacks.py
nametrans/digitstring.py
nametrans/filepathtrans.py
nametrans/fs.py
nametrans/io.py
nametrans/main.py
nametrans/nametransformer.py
nametrans-0.2.8.dist-info/LICENSE
nametrans-0.2.8.dist-info/METADATA
nametrans-0.2.8.dist-info/WHEEL
nametrans-0.2.8.dist-info/entry_points.txt
nametrans-0.2.8.dist-info/top_level.txt
nametrans-0.2.8.dist-info/RECORD
