Metadata-Version: 2.1
Name: nametrans
Version: 0.2.8
Summary: Rename files with regex search/replace semantics
Home-page: https://github.com/numerodix/nametrans
Author: Martin Matusiak
Author-email: numerodix@gmail.com
License: UNKNOWN
Platform: UNKNOWN
Classifier: License :: OSI Approved :: GNU General Public License v2 (GPLv2)
Classifier: Programming Language :: Python :: 2.6
Classifier: Programming Language :: Python :: 2.7
Classifier: Programming Language :: Python :: 3
Classifier: Programming Language :: Python :: 3.2
Classifier: Programming Language :: Python :: 3.3
Classifier: Programming Language :: Python :: 3.4
Classifier: Programming Language :: Python :: Implementation :: CPython
Requires-Dist: ansicolor
